CHANGES.txt
LICENSE.txt
MANIFEST.in
README.rst
murali_svn_authors.txt
setup.py
BiologicalProcessNetworks.egg-info/PKG-INFO
BiologicalProcessNetworks.egg-info/SOURCES.txt
BiologicalProcessNetworks.egg-info/dependency_links.txt
BiologicalProcessNetworks.egg-info/requires.txt
BiologicalProcessNetworks.egg-info/top_level.txt
bpn/__init__.py
bpn/bpln.py
bpn/cbpn.py
bpn/cli.py
bpn/logconf.py
bpn/parsers.py
bpn/statstools.py
bpn/structures.py
bpn/mcmc/__init__.py
bpn/mcmc/chains.py
bpn/mcmc/defaults.py
bpn/mcmc/mcmcbpn.py
bpn/mcmc/recorders.py
bpn/mcmc/sabpn.py
bpn/mcmc/simulatedannealing.py
bpn/mcmc/states.py
bpn/tests/__init__.py
scripts/bpln
scripts/cbpn
scripts/mcmcbpn
scripts/render_bpln_graph.py
scripts/sabpn
scripts/summarize_bpns.py