Metadata-Version: 1.1
Name: BiologicalProcessNetworks
Version: 1.0a5
Summary: Identify significant connections between biological processes using gene interaction networks.
Home-page: http://pypi.python.org/pypi/BiologicalProcessNetworks
Author: Christopher D. Lasher
Author-email: chris.lasher@gmail.com
License: MIT License
Platform: UNKNOWN
Classifier: Development Status :: 3 - Alpha
Classifier: Intended Audience :: Science/Research
Classifier: License :: OSI Approved :: MIT License
Classifier: Operating System :: OS Independent
Classifier: Programming Language :: Python :: 2.6
Classifier: Programming Language :: Python :: 2.7
Classifier: Topic :: Scientific/Engineering :: Bio-Informatics
